lineident/Controller.py
lineident/__init__.py
lineident/__main__.py
lineident/processor/Processor.py
lineident/processor/__init__.py
lineident-1.3.1.dist-info/LICENSE.md
lineident-1.3.1.dist-info/METADATA
lineident-1.3.1.dist-info/WHEEL
lineident-1.3.1.dist-info/entry_points.txt
lineident-1.3.1.dist-info/top_level.txt
lineident-1.3.1.dist-info/RECORD
