Metadata-Version: 2.1
Name: lineident
Version: 1.3.1
Summary: Searches files line by line for given words
Home-page: https://github.com/5f0ne/lineident
Author: 5f0
License: MIT
Classifier: Operating System :: OS Independent 
Classifier: Programming Language :: Python :: 3 
Classifier: License :: OSI Approved :: MIT License 
License-File: LICENSE.md
Requires-Dist: hash-calc
